<item>
<title>Abbtak TV</title>
<link>rtmp://77.92.87.245:1935/live/ playpath=abbtakkLive.stream swfUrl=http://www.abbtakk.tv/wp-content/plugins/ultimate-coming-soon-page/inc/template/jwplayer.flash.swf live=true timeout=15 pageUrl=http://live.abbtakk.tv/</link>
<thumbnail>http://www.pakistanmediaupdates.com/wp-content/uploads/2013/04/abb-takk.jpg</thumbnail>
</item>

<item>
<title>ARY Digital</title>
<link>rtmp://93.174.93.58/zecastEd playpath=digary8 swfUrl=http://zecast.tv/swfs/player.swf pageUrl=http://zecast.tv/embed.php?file=digary8&width=600&height=470 live=true timeout=15</link>
<thumbnail>http://takatuk.com/wp-content/uploads/2008/09/ary-digital-tv-logo.gif</thumbnail>
</item>

<item>
<title>Ary Digital (2)</title>
<link>rtmp://93.174.93.58/zecastEd/digitalary3 live=1 swfUrl=http://zecast.tv/swfs/player.swf pageUrl=http://zecast.tv/embed.php timeout=15</link>
<thumbnail>http://i1112.photobucket.com/albums/k487/thiany25/ary.jpg.png</thumbnail>
</item>

<item>
<title>ARY News</title>
<link>rtmp://server1.arylive.com:1935/live/ playpath=myStream swfUrl=http://p.jwpcdn.com/6/5/jwplayer.flash.swf pageUrl=http://live.arylive.com/stream5.html live=true timeout=15</link>
<thumbnail>http://www.agahiawards.com/2012/channels/ary_news.jpg</thumbnail>
</item>

<item>
<title>ARY QTV</title>
<link>rtmp://server2.arylive.com:1935/live playpath=myStream swfUrl=http://p.jwpcdn.com/6/5/jwplayer.flash.swf live=true timeout=15 pageUrl=http://qtv.arylive.com/live/qtv.html=true</link>
<thumbnail>http://uk.arydigital.tv/images/qtvlogo.jpg</thumbnail>
</item>

<item>
<title>Capital TV Live</title>
<link>rtmp://184.107.236.10:1935/live/ playpath=myStream.sdp swfUrl=http://p.jwpcdn.com/6/4/jwplayer.flash.swf live=true timeout=15 pageUrl=http://www.hamariweb.com/pakistan-tv-channels/capital_tv_live.aspx</link>
<thumbnail>http://www.saach.tv/wp-content/uploads/2013/04/Capital-TV-Pakistan.png</thumbnail>
</item>

<item>
<title>Dunya TV</title>
<link>rtmp://173.245.68.50/live playpath=cam swfUrl=http://dunyanews.tv/newsite/live_stream/player.swf pageUrl=http://dunyanews.tv/newsite/live_stream/ live=true swfVfy=true timeout=15</link>
<thumbnail>http://dunyanews.tv/images/dunyalogo.png</thumbnail>
</item>

<!--<item>
<title>Express News</title>
<link>rtmp://94.102.51.78/live33 playpath=w_enews swfUrl=http://www.zstream.eu/p387sj9hd803ns9n3is93s9df8nd93d9g9dfg94ng949f.swf pageUrl=http://www.zstream.eu/embed.php?v=w_enews&vw=600&vh=450&video=0&domain=www.pogotv.eu live=true timeout=15</link>
<thumbnail> </thumbnail>
</item>-->

<item>
<title>Express Entertainment</title>
<link>rtmp://94.242.228.22:1935/cdn2 playpath=express56 swfUrl=http://liveview365.tv/jwplayer/player.swf pageUrl=http://liveview365.tv/embedded?id=express56&width=600&height=470&domain=desistreams.tv live=true timeout=15</link>
<thumbnail> </thumbnail>
</item>

<item>
<title>Express Entertainment (2)</title>
<link>rtmp://94.102.51.78/live33 playpath=w_express swfUrl=http://www.zstream.eu/p387sj9hd803ns9n3is93s9df8nd93d9g9dfg94ng949f.swf pageUrl=http://www.zstream.eu/embed.php?v=w_express&vw=600&vh=450&video=0&domain=pogotv.eu live=true timeout=15</link>
<thumbnail> </thumbnail>
</item>

<item>
<title>Geo Entertainment</title>
<link>rtmp://188.122.91.6/app playpath=entgeo6 swfUrl=http://www.yocast.tv/player/player-licensed.swf live=true timeout=15 pageUrl=http://www.yocast.tv/embed.php?live=entgeo6 live=true timeout=15</link>
<thumbnail>http://www.tvcorners.com/wp-content/uploads/2012/08/Geo-TV-live-streaming.jpg</thumbnail>
</item>

<!--<item>
<title>Geo Tez TV</title>
<link>rtmp://zeenatlive.viddillions.com/zeenatlive/ playpath=51ztvlive70.stream swfUrl=http://www.longtailvideo.com/jwplayer/jwplayer.flash.swf live=true timeout=15 pageUrl=http://nowwatchtvlive.com/2013/05/geo-tez-live-streaming-watch-geo-tez-pakistan-online-free/</link>
<thumbnail>http://www.pmm.net.pk/wp-content/uploads/2013/04/geo_tez.jpg</thumbnail>
</item>-->

<!--<item>
<title>Geo Super</title>
<link>rtmp://94.102.51.78/live33/ playpath=w_geosuper swfUrl=http://www.zstream.eu/p387sj9hd803ns9n3is93s9df8nd93d9g9dfg94ng949f.swf pageUrl=http://www.zstream.eu/embed.php?v=w_geosuper&vw=600&vh=450&video=0&domain=pogotv.eu live=true timeout=15</link>
<thumbnail> </thumbnail>
</item>-->

<item>
<title>GEO News</title>
<link>rtmp://93.174.93.58/zecastEd playpath=newsgeo8 swfUrl=http://zecast.tv/swfs/player.swf pageUrl=http://zecast.tv/embed.php?file=newsgeo8&width=600&height=470 live=true timeout=15</link>
<thumbnail> </thumbnail>
</item>

<item>
<title>GEO TV</title>
<link>rtmp://93.174.93.58/zecastEd/ playpath=geotv3 swfUrl=http://zecast.tv/swfs/player.swf pageUrl=http://zecast.tv/embed.php?file=geotv3&width=600&height=470 swfVfy=true live=true timeout=15</link>
<thumbnail> </thumbnail>
</item>

<item>
<title>GEO TV (2)</title>
<link>rtmp://94.102.56.186/zecastEd playpath=geotv3 swfUrl=http://zecast.tv/swfs/player.swf pageUrl=http://zecast.tv/embed.php?file=geotv3&width=600&height=470 live=true timeout=15</link>
<thumbnail> </thumbnail>
</item>

<item>
<title>Hum TV</title>
<link>rtmp://93.174.93.58/zecastEd/ playpath=tvhum3 swfUrl=http://zecast.tv/swfs/player.swf pageUrl=http://zecast.tv/embed.php?file=tvhum3&width=600&height=470 swfVfy=true live=true timeout=15</link>
<thumbnail>http://upload.wikimedia.org/wikipedia/en/1/12/Hum_tv.png</thumbnail>
</item>

<item>
<title>Hum TV (2)</title>
<link>rtmp://f.acaster.tv/live playpath=tvhum5 swfUrl=http://www.acaster.tv/player/mplayer327.swf pageUrl=http://www.acaster.tv/embed.php?v=tvhum5&vw=600&vh=470&domain=http://desistreams.tv/embed/hum_tv.ph live=true timeout=15</link>
<thumbnail>http://images3.wikia.nocookie.net/__cb20111001232340/logopedia/images/thumb/4/4c/Hum_TV.png/150px-Hum_TV.png</thumbnail>
</item>

<item>
<title>Hum Masaala</title>
<link>rtmp://streamer35.eboundservices.com/masalatv?wmsAuthSign=c2VydmVyX3RpbWU9Ny81LzIwMTMgMTE6NTc6MTQgUE0maGFzaF92YWx1ZT0rNGxaVEVkeXArakZaNm9oeTFQMnFRPT0mdmFsaWRtaW51dGVzPTIw playpath=masalatv swfUrl=http://www.eboundservices.com/live/player.swf?referrerUri=http://www.eboundservices.com:8888/users/masalatv/masalatv_iframe.html pageUrl=http://www.eboundservices.com/iframe/new/iframe.php?streamer=streamer35&app=masalatv&stream=masalatv&width=640&height=360 live=true timeout=15</link>
<thumbnail> </thumbnail>
</item>

<item>
<title>Kashish TV</title>
<link>rtmp://watch.dmasti.pk/kashish playpath=kashish swfUrl=http://ktntv.tv/ktnnews/player/player.swf pageUrl=http://ktntv.tv/kashish live=1</link>
<thumbnail>http://ktntv.tv/kashish/wp-content/uploads/2012/08/kss-logo.png</thumbnail>
</item>

<item>
<title>NICK</title>
<link>rtmp://94.242.228.40:1930/live2 playpath=nicks.stream swfUrl=http://zonytvcom.info/saki2/player/player-licensed.swf live=true timeout=15 pageUrl=http://zonytvcom.info/saki/embed.php?live=nicks.stream</link>
<thumbnail>http://i1.cdnds.net/10/15/M/tv_nick_logo.jpg</thumbnail>
</item>

<item>
<title>Prime TV</title>
<link>http://46.249.213.93/iPhone/broadcast/primetv-tablet.3gp/primetv-tablet.3gp-mr648k.m3u8?trackingid=3801820000&os=desktop&m3usessid=f054d17cfd429541e5d0e4b7748ba9e2&len=36&gtime=1370053222&guid=bca719c0ac8f4030ffe9123456789012&da=0&hk=F07431CF523A23B6AB4B497B9FD08F1F</link>
<thumbnail>http://www.lyngsat-logo.com/logo/tv/pp/prime_tv_uk.jpg</thumbnail>
</item>

<item>
<title>PTV Home</title>
<link>rtmp://live.server4sale.com/live playpath=PTVhome swfUrl=http://live.server4sale.com:81/swfs/videoPlayer.swf pageUrl=http://home.ptv.com.pk/ live=1</link>
<thumbnail>http://www.sehartv.com/wp-content/uploads/2012/10/ptv-home.jpg</thumbnail>
</item>

<item>
<title>PTV Home (2)</title>
<link>rtmp://s4s1.pakistanvision.tv/live playpath=PTVhome swfUrl=http://www.pakistanvision.com/swfs/videoPlayer.swf pageUrl=http://ptv.com.pk/PTVHOME-live.asp swfVfy=true live=true timeout=15</link>
<thumbnail>http://www.lyngsat-logo.com/logo/tv/pp/ptv_home.jpg</thumbnail>
</item>

<item>
<title>PTV News</title>
<link>rtmp://s4s1.pakistanvision.tv/live playpath=PTVnews swfUrl=http://www.pakistanvision.com/swfs/videoPlayer.swf pageUrl=http://ptv.com.pk/livetvnews.asp swfVfy=true live=true timeout=15</link>
<thumbnail>http://www.lyngsat-logo.com/logo/tv/pp/ptv_news.jpg</thumbnail>
</item>

<item>
<title>PTV Sports</title>
<link>rtmp://46.246.124.25/live/sportsptv live=1 swfUrl=http://www.acaster.tv/player/mplayer327.sw pageUrl=http://www.acaster.tv/embed.php timeout=15</link>
<thumbnail>http://i1112.photobucket.com/albums/k487/thiany25/PTVsports.jpg.png</thumbnail>
</item>

<item>
<title>SAMAA News</title>
<link>rtmp://85.12.5.7/vl/_definst_ playpath=samanews867 swfUrl=http://www.veemi.com/player/player-licensed.swf pageUrl=http://www.veemi.com/embed.php?v=samanews867&vw=600&vh=470&domain=desistreams.tv live=true timeout=15</link>
<thumbnail> </thumbnail>
</item>
<item>

<title>SAMAA TV</title>
<link>rtmp://38.96.148.99:1935/samaalive/samaalive live=1 swfUrl=http://live.samaa.tv/player.swf pageUrl=http://live.samaa.tv/ timeout=15</link>
<thumbnail>http://i1112.photobucket.com/albums/k487/thiany25/samaatv_logo.png</thumbnail>
</item>
